setup.py
glusterlog/__init__.py
glusterlog/colorize.py
glusterlog/parser.py
glusterlog/tojson.py
glusterlog.egg-info/PKG-INFO
glusterlog.egg-info/SOURCES.txt
glusterlog.egg-info/dependency_links.txt
glusterlog.egg-info/entry_points.txt
glusterlog.egg-info/not-zip-safe
glusterlog.egg-info/top_level.txt