Metadata-Version: 1.1
Name: glusterlog
Version: 0.2
Summary: Gluster Log parser
Home-page: https://github.com/aravindavk/glusterlog
Author: Aravinda VK
Author-email: avishwan@redhat.com
License: GPLv2
Keywords: gluster,tool,logs
Platform: linux
Classifier: Development Status :: 3 - Alpha
Classifier: Topic :: Utilities
Classifier: Environment :: Console
Classifier: License :: OSI Approved :: MIT License
Classifier: Operating System :: POSIX :: Linux
Classifier: Programming Language :: Python
Classifier: Programming Language :: Python :: 2.6
Classifier: Programming Language :: Python :: 2.7
Classifier: Programming Language :: Python :: 2 :: Only
